prime_checker/__init__.py
prime_checker/core.py
unique_prime_checker-0.1.0.dist-info/LICENSE
unique_prime_checker-0.1.0.dist-info/METADATA
unique_prime_checker-0.1.0.dist-info/WHEEL
unique_prime_checker-0.1.0.dist-info/top_level.txt
unique_prime_checker-0.1.0.dist-info/RECORD
