Metadata-Version: 2.1
Name: unique-prime-checker
Version: 0.1.0
Summary: A simple library to check if a number is prime
Home-page: https://github.com/koratvivek/prime_checker
Author: vivek korat
Author-email: koratvivek0@gmail.com
Classifier: Programming Language :: Python :: 3
Classifier: License :: OSI Approved :: MIT License
Classifier: Operating System :: OS Independent
Requires-Python: >=3.7
License-File: LICENSE
